scrapealong/__init__.py
scrapealong/base.py
scrapealong/common.py
scrapealong/core.py
scrapealong/fetch.py
scrapealong/froxyWrapper.py
scrapealong/helpers.py
scrapealong/models.py
scrapealong/proxyscrapeWrapper.py
scrapealong/settings.py
scrapealong/settings_private.py
scrapealong-0.1.7.dist-info/LICENSE
scrapealong-0.1.7.dist-info/METADATA
scrapealong-0.1.7.dist-info/WHEEL
scrapealong-0.1.7.dist-info/top_level.txt
scrapealong-0.1.7.dist-info/RECORD
